floodrisk/__init__.py
floodrisk/damage_assess.py
floodrisk/export_utils.py
floodrisk/flood_detect.py
floodrisk/floodrisk_cli.py
floodrisk/gee_auth.py
floodrisk/visualization.py
floodrisk-1.0.0.dist-info/licenses/LICENSE
floodrisk-1.0.0.dist-info/METADATA
floodrisk-1.0.0.dist-info/WHEEL
floodrisk-1.0.0.dist-info/entry_points.txt
floodrisk-1.0.0.dist-info/top_level.txt
floodrisk-1.0.0.dist-info/RECORD
