Metadata-Version: 2.4
Name: floodrisk
Version: 1.0.0
Summary: Flood detection and damage assessment using Sentinel-1 SAR and OSM data with Google Earth Engine
Home-page: https://github.com/MeawMan/floodrisk
Author: Mahfujur Rahman Joy
Author-email: Mahfujur Rahman Joy <mahfujurjoy@example.com>
License: MIT
Project-URL: Homepage, https://github.com/MeawMan/floodrisk
Project-URL: Documentation, https://github.com/MeawMan/floodrisk
Project-URL: PyPI, https://pypi.org/project/floodrisk/
Project-URL: DOI, https://doi.org/10.5281/zenodo.16407193
Keywords: flood,Sentinel-1,SAR,OSM,Google Earth Engine,GIS
Classifier: Development Status :: 5 - Production/Stable
Classifier: Programming Language :: Python :: 3
Classifier: License :: OSI Approved :: MIT License
Classifier: Intended Audience :: Science/Research
Classifier: Topic :: Scientific/Engineering :: GIS
Requires-Python: >=3.8
License-File: LICENSE
Requires-Dist: geemap>=0.20.6
Requires-Dist: earthengine-api>=0.1.400
Requires-Dist: osmnx>=1.8.0
Requires-Dist: geopandas>=0.12.0
Requires-Dist: rasterio>=1.3.0
Requires-Dist: shapely>=2.0.0
Requires-Dist: pandas>=1.5.0
Requires-Dist: matplotlib>=3.6.0
Dynamic: author
Dynamic: home-page
Dynamic: license-file
Dynamic: requires-python
